fission_client/__init__.py
fission_client/api_client.py
fission_client/api_response.py
fission_client/configuration.py
fission_client/exceptions.py
fission_client/py.typed
fission_client/rest.py
fission_client/api/__init__.py
fission_client/api/fission_io_v1_api.py
fission_client/models/__init__.py
fission_client/models/io_fission_v1_canary_config.py
fission_client/models/io_fission_v1_canary_config_list.py
fission_client/models/io_fission_v1_canary_config_spec.py
fission_client/models/io_fission_v1_canary_config_status.py
fission_client/models/io_fission_v1_environment.py
fission_client/models/io_fission_v1_environment_list.py
fission_client/models/io_fission_v1_environment_spec.py
fission_client/models/io_fission_v1_environment_spec_builder.py
fission_client/models/io_fission_v1_environment_spec_builder_container.py
fission_client/models/io_fission_v1_environment_spec_builder_container_env_from_inner.py
fission_client/models/io_fission_v1_environment_spec_builder_container_env_from_inner_config_map_ref.py
fission_client/models/io_fission_v1_environment_spec_builder_container_env_from_inner_secret_ref.py
fission_client/models/io_fission_v1_environment_spec_builder_container_env_inner.py
fission_client/models/io_fission_v1_environment_spec_builder_container_env_inner_value_from.py
fission_client/models/io_fission_v1_environment_spec_builder_container_env_inner_value_from_config_map_key_ref.py
fission_client/models/io_fission_v1_environment_spec_builder_container_env_inner_value_from_field_ref.py
fission_client/models/io_fission_v1_environment_spec_builder_container_env_inner_value_from_resource_field_ref.py
fission_client/models/io_fission_v1_environment_spec_builder_container_env_inner_value_from_secret_key_ref.py
fission_client/models/io_fission_v1_environment_spec_builder_container_lifecycle.py
fission_client/models/io_fission_v1_environment_spec_builder_container_lifecycle_post_start.py
fission_client-1.0.6.dist-info/METADATA
fission_client-1.0.6.dist-info/WHEEL
fission_client-1.0.6.dist-info/top_level.txt
fission_client-1.0.6.dist-info/RECORD
